japps/__init__.py
japps/configuration.py
japps/configuration.pyi
japps/errors.py
japps/errors.pyi
japps/log.py
japps/log.pyi
japps/plugin_config_parsers.py
japps/plugin_config_parsers.pyi
japps/pluginloaders.py
japps/pluginloaders.pyi
japps/pluginmanager.py
japps/pluginmanager.pyi
japps/plugins.py
japps/plugins.pyi
japps/runners.py
japps/runners.pyi
japps/utils.py
japps/utils.pyi
japps-0.0.6.dist-info/LICENSE
japps-0.0.6.dist-info/METADATA
japps-0.0.6.dist-info/WHEEL
japps-0.0.6.dist-info/top_level.txt
japps-0.0.6.dist-info/RECORD
