Metadata-Version: 2.1
Name: japps
Version: 0.0.6
Summary: Simple support for complicated plugins
Author-email: OlegSuperBro <olegrakovic323@gmail.com>
Project-URL: Homepage, https://github.com/OlegSuperBro/japps
Project-URL: Bug Tracker, https://github.com/OlegSuperBro/japps/issues
Classifier: Programming Language :: Python :: 3
Classifier: License :: OSI Approved :: MIT License
Classifier: Operating System :: OS Independent
Requires-Python: >=3.8
License-File: LICENSE
Requires-Dist: typing-extensions ==4.7.1
